async_stream_processing/__init__.py
async_stream_processing/processor.py
async_stream_processing/testing.py
async_stream_processing-1.0.0.dist-info/METADATA
async_stream_processing-1.0.0.dist-info/WHEEL
async_stream_processing-1.0.0.dist-info/RECORD
