Metadata-Version: 2.4
Name: async-stream-processing
Version: 1.0.0
Summary: Asynchronous (Event) Stream Processing. Allows event stream processors easily.
Project-URL: Homepage, https://github.com/pytek-io/asp
Author-email: fdv1 <francois@pytek.io>
Keywords: asyncio,backtesting,event processing
Requires-Python: >=3.8
